odoo/addons/sale_order_pricelist_tracking/README.rst
odoo/addons/sale_order_pricelist_tracking/__init__.py
odoo/addons/sale_order_pricelist_tracking/__manifest__.py
odoo/addons/sale_order_pricelist_tracking/i18n/sale_order_pricelist_tracking.pot
odoo/addons/sale_order_pricelist_tracking/models/__init__.py
odoo/addons/sale_order_pricelist_tracking/models/sale_order.py
odoo/addons/sale_order_pricelist_tracking/readme/CONTRIBUTORS.rst
odoo/addons/sale_order_pricelist_tracking/readme/DESCRIPTION.rst
odoo/addons/sale_order_pricelist_tracking/static/description/icon.png
odoo/addons/sale_order_pricelist_tracking/static/description/index.html
odoo13_addon_sale_order_pricelist_tracking-13.0.1.0.1.dev5.dist-info/METADATA
odoo13_addon_sale_order_pricelist_tracking-13.0.1.0.1.dev5.dist-info/WHEEL
odoo13_addon_sale_order_pricelist_tracking-13.0.1.0.1.dev5.dist-info/top_level.txt
odoo13_addon_sale_order_pricelist_tracking-13.0.1.0.1.dev5.dist-info/RECORD
